redhat_tar_xz_extractor/Redhat.py
redhat_tar_xz_extractor/__init__.py
redhat_tar_xz_extractor-1.0.0.dist-info/METADATA
redhat_tar_xz_extractor-1.0.0.dist-info/WHEEL
redhat_tar_xz_extractor-1.0.0.dist-info/top_level.txt
redhat_tar_xz_extractor-1.0.0.dist-info/RECORD
