Metadata-Version: 2.1
Name: redhat-tar-xz-extractor
Version: 1.0.0
Summary: tarfile.xz file extractor use case for redhat feature
Home-page: UNKNOWN
Author: Aryanshu verma
Author-email: aryanshu.verma@dell.com
License: UNKNOWN
Platform: UNKNOWN
Requires-Dist: tarfile
